myretz/__init__.py
myretz/core/__init__.py
myretz/core/commons/__init__.py
myretz_core-0.1.0.dist-info/licenses/LICENSE
myretz_core-0.1.0.dist-info/METADATA
myretz_core-0.1.0.dist-info/WHEEL
myretz_core-0.1.0.dist-info/top_level.txt
myretz_core-0.1.0.dist-info/RECORD
