Metadata-Version: 2.4
Name: myretz.core
Version: 0.1.0
Summary: MyRets是 My Returns 的简写，希望能够高效、简便为个人（MY）获得收益（Returns）；myretz.core是其核心模块，提供基础工具（数据结构、日志、通用函数）服务
Author-email: Jeffrey Wang <shwangjj@163.com>
Project-URL: Homepage, https://gitee.com/yourusername/myretz.core
Project-URL: Bug Tracker, https://gitee.com/yourusername/myretz.core/issues
Classifier: Programming Language :: Python :: 3
Classifier: License :: OSI Approved :: Apache Software License
Classifier: Operating System :: OS Independent
Requires-Python: >=3.7
License-File: LICENSE
Dynamic: license-file
